tuttle/__init__.py
tuttle/app.py
tuttle/banking.py
tuttle/billing.py
tuttle/calendar.py
tuttle/cloud.py
tuttle/context.py
tuttle/dataviz.py
tuttle/dev.py
tuttle/forecast.py
tuttle/invoice.py
tuttle/invoicing.py
tuttle/mail.py
tuttle/model.py
tuttle/project.py
tuttle/rendering.py
tuttle/schema.py
tuttle/social_insurance.py
tuttle/tax.py
tuttle/time.py
tuttle/timetracking.py
tuttle/ui.py
tuttle/view.py
tuttle-0.0.11.dist-info/LICENSE
tuttle-0.0.11.dist-info/METADATA
tuttle-0.0.11.dist-info/WHEEL
tuttle-0.0.11.dist-info/top_level.txt
tuttle-0.0.11.dist-info/RECORD
