Metadata-Version: 2.1
Name: tuttle
Version: 0.0.11
Summary: Painless business planning for freelancers.
Home-page: https://github.com/tuttle-dev/tuttle
Author: Christian Staudt
Author-email: mail@clstaudt.me
License: GNU General Public License v3
Keywords: tuttle
Classifier: Development Status :: 2 - Pre-Alpha
Classifier: Intended Audience :: Developers
Classifier: License :: OSI Approved :: GNU General Public License v3 (GPLv3)
Classifier: Natural Language :: English
Classifier: Programming Language :: Python :: 3
Classifier: Programming Language :: Python :: 3.8
Classifier: Programming Language :: Python :: 3.9
Classifier: Programming Language :: Python :: 3.10
Requires-Python: >=3.8
License-File: LICENSE
Requires-Dist: pytest
Requires-Dist: pandas
Requires-Dist: altair
Requires-Dist: pydantic
Requires-Dist: sqlalchemy (==1.4.35)
Requires-Dist: sqlmodel
Requires-Dist: pyicloud
Requires-Dist: fints
Requires-Dist: ics
Requires-Dist: babel
Requires-Dist: loguru
Requires-Dist: pdfkit
